shioajicaller/__init__.py
shioajicaller/caller.py
shioajicaller/cli/__init__.py
shioajicaller/codes/__init__.py
shioajicaller/codes/update.py
shioajicaller/config.py
shioajicaller/server/__init__.py
shioajicaller/server/websocket.py
shioajicaller-0.4.2.3.dist-info/LICENSE
shioajicaller-0.4.2.3.dist-info/METADATA
shioajicaller-0.4.2.3.dist-info/WHEEL
shioajicaller-0.4.2.3.dist-info/entry_points.txt
shioajicaller-0.4.2.3.dist-info/RECORD
