Metadata-Version: 2.1
Name: shioajicaller
Version: 0.4.2.3
Summary: shioaj warp caller
Home-page: https://github.com/SDpower/shioajicaller
License: MIT
Author: Steve Lo
Author-email: info@sd.idv.tw
Requires-Python: >=3.10,<4.0
Classifier: License :: OSI Approved :: MIT License
Classifier: Programming Language :: Python :: 3
Classifier: Programming Language :: Python :: 3.10
Classifier: Programming Language :: Python :: 3.11
Classifier: Programming Language :: Python :: 3.12
Classifier: Programming Language :: Python :: 3.13
Requires-Dist: gmqtt (>=0.6.16,<0.7.0)
Requires-Dist: orjson (>=3.9.2,<4.0.0)
Requires-Dist: python-dotenv (>=0.19.0,<0.20.0)
Requires-Dist: redis (>=5.2.0,<6.0.0)
Requires-Dist: shioaji[speed] (>=1.2.5,<2.0.0)
Requires-Dist: uvloop (>=0.21.0,<0.22.0) ; sys_platform == "linux"
Requires-Dist: websockets (>=13.0,<14.0)
Project-URL: Repository, https://github.com/SDpower/shioajicaller
